setup.cfg
setup.py
LztApi/LolzApi.py
LztApi/__init__.py
LztApi.egg-info/PKG-INFO
LztApi.egg-info/SOURCES.txt
LztApi.egg-info/dependency_links.txt
LztApi.egg-info/not-zip-safe
LztApi.egg-info/top_level.txt