Metadata-Version: 2.1
Name: LztApi
Version: 1.0
Summary: LolzTeam Api
Author-email: coder@derkown.ru
